napari_manual_split_and_merge_labels/__init__.py
napari_manual_split_and_merge_labels/_function.py
napari_manual_split_and_merge_labels/_tests/__init__.py
napari_manual_split_and_merge_labels/_tests/test_function.py
napari_manual_split_and_merge_labels-0.1.4.dist-info/LICENSE
napari_manual_split_and_merge_labels-0.1.4.dist-info/METADATA
napari_manual_split_and_merge_labels-0.1.4.dist-info/WHEEL
napari_manual_split_and_merge_labels-0.1.4.dist-info/top_level.txt
napari_manual_split_and_merge_labels-0.1.4.dist-info/RECORD
